test_CaesarCoder/__init__.py
test324_CaesarCoder-0.1.dist-info/METADATA
test324_CaesarCoder-0.1.dist-info/WHEEL
test324_CaesarCoder-0.1.dist-info/top_level.txt
test324_CaesarCoder-0.1.dist-info/RECORD
