Metadata-Version: 2.1
Name: test324-CaesarCoder
Version: 0.1
Summary: str Saeser coder-decoder
Home-page: UNKNOWN
Author: dakinevich
Author-email: ivan7855060@gmail.com
License: UNKNOWN
Platform: UNKNOWN
Classifier: Programming Language :: Python :: 3
Classifier: License :: OSI Approved :: MIT License
Classifier: Operating System :: OS Independent
Requires-Python: >=3.6
